pydebuggerconfig/__init__.py
pydebuggerconfig/backend.py
pydebuggerconfig/baseconfig.py
pydebuggerconfig/boardconfig.py
pydebuggerconfig/deviceconfig.py
pydebuggerconfig/extension_id_tool.py
pydebuggerconfig/extension_id_tool_main.py
pydebuggerconfig/logging.yaml
pydebuggerconfig/pydebuggerconfig.py
pydebuggerconfig/pydebuggerconfig_errors.py
pydebuggerconfig/pydebuggerconfig_main.py
pydebuggerconfig/board-configs/ATmega4809-CNANO.xml
pydebuggerconfig/board-configs/ATtiny1607-CNANO.xml
pydebuggerconfig/board-configs/ATtiny1627-CNANO.xml
pydebuggerconfig/board-configs/ATtiny3217-CNANO.xml
pydebuggerconfig/board-configs/AVR-BLE.xml
pydebuggerconfig/board-configs/AVR-IoT_Cellular-Mini.xml
pydebuggerconfig/board-configs/AVR-IoT_WA.xml
pydebuggerconfig/board-configs/AVR-IoT_WG.xml
pydebuggerconfig/board-configs/AVR128DA48-CNANO.xml
pydebuggerconfig/board-configs/AVR128DB48-CNANO.xml
pydebuggerconfig/board-configs/AVR16EB32-CNANO.xml
pydebuggerconfig/board-configs/AVR64DD32-CNANO.xml
pydebuggerconfig/board-configs/AVR64DU32-CNANO.xml
pydebuggerconfig/board-configs/AVR64EA48-CNANO.xml
pydebuggerconfig/board-configs/CIP_Hybrid_Power_PIM.xml
pydebuggerconfig/board-configs/CIP_Hybrid_Power_STK.xml
pydebuggerconfig/board-configs/CryptoAuthTrust.xml
pydebuggerconfig/board-configs/CryptoAuthTrustManager.xml
pydebuggerconfig/board-configs/EBV_IOT.xml
pydebuggerconfig/board-configs/PIC-BLE.xml
pydebuggerconfig/board-configs/PIC-IoT_WA.xml
pydebuggerconfig/board-configs/PIC-IoT_WG.xml
pydebuggerconfig/board-configs/PIC16F13145-CNANO.xml
pydebuggerconfig/board-configs/PIC16F15244-CNANO.xml
pydebuggerconfig/board-configs/PIC16F15276-CNANO.xml
pydebuggerconfig/board-configs/PIC16F15376-CNANO.xml
pydebuggerconfig/board-configs/PIC16F17146-CNANO.xml
pydebuggerconfig/board-configs/PIC16F18076-CNANO.xml
pydebuggerconfig/board-configs/PIC16F18446-CNANO.xml
pydebuggerconfig/board-configs/PIC16F18446-XPRESS.xml
pydebuggerconfig/board-configs/PIC18F16Q20-CNANO.xml
pydebuggerconfig-3.11.2.44.dist-info/LICENSE.txt
pydebuggerconfig-3.11.2.44.dist-info/METADATA
pydebuggerconfig-3.11.2.44.dist-info/WHEEL
pydebuggerconfig-3.11.2.44.dist-info/entry_points.txt
pydebuggerconfig-3.11.2.44.dist-info/top_level.txt
pydebuggerconfig-3.11.2.44.dist-info/RECORD
