Metadata-Version: 2.1
Name: pydebuggerconfig
Version: 3.11.2.44
Summary: A collection of tools to configure Microchip PKOB nano on-board debuggers
Author: Microchip Technology
Author-email: support@microchip.com
License: MIT
Keywords: Microchip,nEDBG,Curiosity Nano,PKOB nano,debugger
Classifier: Development Status :: 5 - Production/Stable
Classifier: Intended Audience :: Developers
Classifier: Topic :: Software Development :: Embedded Systems
Classifier: Programming Language :: Python :: 3
Classifier: Programming Language :: Python :: 3.8
Classifier: Programming Language :: Python :: 3.9
Classifier: Programming Language :: Python :: 3.10
Classifier: Programming Language :: Python :: 3.11
Classifier: Programming Language :: Python :: 3.12
Classifier: Operating System :: Microsoft :: Windows
Classifier: Operating System :: POSIX :: Linux
Classifier: Operating System :: MacOS
Classifier: License :: OSI Approved :: MIT License
Requires-Python: >=2.7
License-File: LICENSE.txt
Requires-Dist: crcmod
Requires-Dist: packaging
Requires-Dist: IntelHex
Requires-Dist: PyYAML
Requires-Dist: appdirs
Requires-Dist: pyedbglib >=2.15
Requires-Dist: xmlschema ==1.0.18 ; python_version < "3"
Requires-Dist: pathlib2 ; python_version < "3"
Requires-Dist: xmlschema ; python_version >= "3"
Provides-Extra: dev
Requires-Dist: pylint >=2.15 ; extra == 'dev'
Provides-Extra: test
Requires-Dist: mock ; extra == 'test'
Requires-Dist: pytest ; extra == 'test'
